FlaskTester.py
flasktester-5.0.dist-info/LICENSE
flasktester-5.0.dist-info/METADATA
flasktester-5.0.dist-info/WHEEL
flasktester-5.0.dist-info/top_level.txt
flasktester-5.0.dist-info/RECORD
