Metadata-Version: 2.2
Name: FlaskTester
Version: 5.0
Summary: Pytest fixtures for Flask internal and external authenticated tests
Author-email: Fabien Coelho <flask.tester@coelho.net>
License: CC0
Project-URL: repository, https://github.com/zx80/flask-tester
Project-URL: documentation, https://zx80.github.io/flask-tester/
Project-URL: issues, https://github.com/zx80/flask-tester/issues
Project-URL: package, https://pypi.org/project/FlaskTester/
Classifier: Development Status :: 5 - Production/Stable
Classifier: Intended Audience :: Developers
Classifier: License :: CC0 1.0 Universal (CC0 1.0) Public Domain Dedication
Classifier: Programming Language :: Python
Classifier: Environment :: Web Environment
Classifier: Framework :: Flask
Classifier: Topic :: Software Development :: Libraries :: Python Modules
Requires-Python: >=3.10
License-File: LICENSE
Requires-Dist: requests
Requires-Dist: pytest
Provides-Extra: dev
Requires-Dist: mypy; extra == "dev"
Requires-Dist: pyright; extra == "dev"
Requires-Dist: ruff; extra == "dev"
Requires-Dist: coverage; extra == "dev"
Requires-Dist: pymarkdownlnt!=0.9.5; extra == "dev"
Requires-Dist: types-flask; extra == "dev"
Requires-Dist: types-requests; extra == "dev"
Requires-Dist: FlaskSimpleAuth>=35.0; extra == "dev"
Requires-Dist: bcrypt; extra == "dev"
Requires-Dist: pydantic; extra == "dev"
Provides-Extra: doc
Requires-Dist: sphinx; extra == "doc"
Requires-Dist: sphinx_rtd_theme; extra == "doc"
Requires-Dist: sphinx-autoapi; extra == "doc"
Requires-Dist: sphinx-lint; extra == "doc"
Requires-Dist: myst_parser; extra == "doc"
Provides-Extra: pub
Requires-Dist: build; extra == "pub"
Requires-Dist: twine; extra == "pub"
Requires-Dist: wheel; extra == "pub"
